{
  "id": "cadc5652-d97c-44fb-96bd-7f4eed9a2bff",
  "prevId": "d9923c96-950b-428a-abee-0f705b23afc4",
  "version": "7",
  "dialect": "postgresql",
  "tables": {
    "public.batch_invoices": {
      "name": "batch_invoices",
      "schema": "",
      "columns": {
        "batch_id": {
          "name": "batch_id",
          "type": "text",
          "primaryKey": false,
          "notNull": true
        },
        "invoice_id": {
          "name": "invoice_id",
          "type": "text",
          "primaryKey": false,
          "notNull": true
        },
        "source_file": {
          "name": "source_file",
          "type": "text",
          "primaryKey": false,
          "notNull": true
        },
        "created_at": {
          "name": "created_at",
          "type": "timestamp with time zone",
          "primaryKey": false,
          "notNull": true,
          "default": "now()"
        }
      },
      "indexes": {
        "batch_invoices_batch_id_idx": {
          "name": "batch_invoices_batch_id_idx",
          "columns": [
            {
              "expression": "batch_id",
              "isExpression": false,
              "asc": true,
              "nulls": "last"
            }
          ],
          "isUnique": false,
          "concurrently": false,
          "method": "btree",
          "with": {}
        }
      },
      "foreignKeys": {
        "batch_invoices_batch_id_batches_batch_id_fk": {
          "name": "batch_invoices_batch_id_batches_batch_id_fk",
          "tableFrom": "batch_invoices",
          "tableTo": "batches",
          "columnsFrom": [
            "batch_id"
          ],
          "columnsTo": [
            "batch_id"
          ],
          "onDelete": "cascade",
          "onUpdate": "no action"
        },
        "batch_invoices_invoice_id_invoices_invoice_id_fk": {
          "name": "batch_invoices_invoice_id_invoices_invoice_id_fk",
          "tableFrom": "batch_invoices",
          "tableTo": "invoices",
          "columnsFrom": [
            "invoice_id"
          ],
          "columnsTo": [
            "invoice_id"
          ],
          "onDelete": "cascade",
          "onUpdate": "no action"
        }
      },
      "compositePrimaryKeys": {
        "batch_invoices_batch_id_invoice_id_pk": {
          "name": "batch_invoices_batch_id_invoice_id_pk",
          "columns": [
            "batch_id",
            "invoice_id"
          ]
        }
      },
      "uniqueConstraints": {},
      "policies": {},
      "checkConstraints": {},
      "isRLSEnabled": false
    },
    "public.batches": {
      "name": "batches",
      "schema": "",
      "columns": {
        "batch_id": {
          "name": "batch_id",
          "type": "text",
          "primaryKey": true,
          "notNull": true
        },
        "status": {
          "name": "status",
          "type": "batch_status",
          "typeSchema": "public",
          "primaryKey": false,
          "notNull": true,
          "default": "'queued'"
        },
        "file_type": {
          "name": "file_type",
          "type": "text",
          "primaryKey": false,
          "notNull": true
        },
        "file_name": {
          "name": "file_name",
          "type": "text",
          "primaryKey": false,
          "notNull": true
        },
        "file_key": {
          "name": "file_key",
          "type": "text",
          "primaryKey": false,
          "notNull": true
        },
        "source": {
          "name": "source",
          "type": "text",
          "primaryKey": false,
          "notNull": false
        },
        "user_id": {
          "name": "user_id",
          "type": "text",
          "primaryKey": false,
          "notNull": true
        },
        "invoice_count": {
          "name": "invoice_count",
          "type": "integer",
          "primaryKey": false,
          "notNull": false
        },
        "failed_count": {
          "name": "failed_count",
          "type": "integer",
          "primaryKey": false,
          "notNull": false
        },
        "errors": {
          "name": "errors",
          "type": "jsonb",
          "primaryKey": false,
          "notNull": true,
          "default": "'[]'::jsonb"
        },
        "created_at": {
          "name": "created_at",
          "type": "timestamp with time zone",
          "primaryKey": false,
          "notNull": true,
          "default": "now()"
        },
        "completed_at": {
          "name": "completed_at",
          "type": "timestamp with time zone",
          "primaryKey": false,
          "notNull": false
        },
        "file_deleted_at": {
          "name": "file_deleted_at",
          "type": "timestamp with time zone",
          "primaryKey": false,
          "notNull": false
        }
      },
      "indexes": {
        "batches_user_id_created_at_idx": {
          "name": "batches_user_id_created_at_idx",
          "columns": [
            {
              "expression": "user_id",
              "isExpression": false,
              "asc": true,
              "nulls": "last"
            },
            {
              "expression": "created_at",
              "isExpression": false,
              "asc": true,
              "nulls": "last"
            },
            {
              "expression": "batch_id",
              "isExpression": false,
              "asc": true,
              "nulls": "last"
            }
          ],
          "isUnique": false,
          "concurrently": false,
          "method": "btree",
          "with": {}
        }
      },
      "foreignKeys": {},
      "compositePrimaryKeys": {},
      "uniqueConstraints": {},
      "policies": {},
      "checkConstraints": {},
      "isRLSEnabled": false
    },
    "public.invoices": {
      "name": "invoices",
      "schema": "",
      "columns": {
        "invoice_id": {
          "name": "invoice_id",
          "type": "text",
          "primaryKey": true,
          "notNull": true
        },
        "user_id": {
          "name": "user_id",
          "type": "text",
          "primaryKey": false,
          "notNull": true
        },
        "invoice_number": {
          "name": "invoice_number",
          "type": "text",
          "primaryKey": false,
          "notNull": true
        },
        "type": {
          "name": "type",
          "type": "text",
          "primaryKey": false,
          "notNull": true
        },
        "currency": {
          "name": "currency",
          "type": "char(3)",
          "primaryKey": false,
          "notNull": true
        },
        "total_amount": {
          "name": "total_amount",
          "type": "numeric(15, 2)",
          "primaryKey": false,
          "notNull": true
        },
        "issued_at": {
          "name": "issued_at",
          "type": "timestamp with time zone",
          "primaryKey": false,
          "notNull": true
        },
        "issuer_name": {
          "name": "issuer_name",
          "type": "text",
          "primaryKey": false,
          "notNull": true
        },
        "issuer_nit": {
          "name": "issuer_nit",
          "type": "text",
          "primaryKey": false,
          "notNull": true
        },
        "client_name": {
          "name": "client_name",
          "type": "text",
          "primaryKey": false,
          "notNull": true
        },
        "client_nit": {
          "name": "client_nit",
          "type": "text",
          "primaryKey": false,
          "notNull": true
        },
        "line_items": {
          "name": "line_items",
          "type": "jsonb",
          "primaryKey": false,
          "notNull": true,
          "default": "'[]'::jsonb"
        },
        "raw_payload": {
          "name": "raw_payload",
          "type": "jsonb",
          "primaryKey": false,
          "notNull": true,
          "default": "'{}'::jsonb"
        },
        "created_at": {
          "name": "created_at",
          "type": "timestamp with time zone",
          "primaryKey": false,
          "notNull": true,
          "default": "now()"
        }
      },
      "indexes": {
        "invoices_invoice_number_user_id_idx": {
          "name": "invoices_invoice_number_user_id_idx",
          "columns": [
            {
              "expression": "invoice_number",
              "isExpression": false,
              "asc": true,
              "nulls": "last"
            },
            {
              "expression": "user_id",
              "isExpression": false,
              "asc": true,
              "nulls": "last"
            }
          ],
          "isUnique": true,
          "concurrently": false,
          "method": "btree",
          "with": {}
        }
      },
      "foreignKeys": {},
      "compositePrimaryKeys": {},
      "uniqueConstraints": {},
      "policies": {},
      "checkConstraints": {},
      "isRLSEnabled": false
    }
  },
  "enums": {
    "public.batch_status": {
      "name": "batch_status",
      "schema": "public",
      "values": [
        "queued",
        "processing",
        "done",
        "failed"
      ]
    }
  },
  "schemas": {},
  "sequences": {},
  "roles": {},
  "policies": {},
  "views": {},
  "_meta": {
    "columns": {},
    "schemas": {},
    "tables": {}
  }
}